kafe2/__init__.py
kafe2/tools.py
kafe2/config/__init__.py
kafe2/config/kafe2.matplotlibrc.conf
kafe2/config/kafe2.yaml
kafe2/config/plot_style_color.yaml
kafe2/core/__init__.py
kafe2/core/confidence.py
kafe2/core/constraint.py
kafe2/core/contour.py
kafe2/core/error.py
kafe2/core/fitters/__init__.py
kafe2/core/fitters/nexus.py
kafe2/core/fitters/nexus_fitter.py
kafe2/core/fitters/simple_fitter.py
kafe2/core/minimizers/__init__.py
kafe2/core/minimizers/iminuit_minimizer.py
kafe2/core/minimizers/minimizer_base.py
kafe2/core/minimizers/root_tminuit_minimizer.py
kafe2/core/minimizers/scipy_optimize_minimizer.py
kafe2/fit/__init__.py
kafe2/fit/_aux.py
kafe2/fit/_base/__init__.py
kafe2/fit/_base/container.py
kafe2/fit/_base/cost.py
kafe2/fit/_base/ensemble.py
kafe2/fit/_base/fit.py
kafe2/fit/_base/format.py
kafe2/fit/_base/model.py
kafe2/fit/_base/plot.py
kafe2/fit/custom/__init__.py
kafe2/fit/custom/fit.py
kafe2/fit/histogram/__init__.py
kafe2/fit/histogram/container.py
kafe2/fit/histogram/cost.py
kafe2/fit/histogram/fit.py
kafe2/fit/histogram/model.py
kafe2/fit/histogram/plot.py
kafe2/fit/indexed/__init__.py
kafe2/fit/indexed/container.py
kafe2/fit/indexed/cost.py
kafe2/fit/indexed/fit.py
kafe2/fit/indexed/format.py
kafe2/fit/indexed/model.py
kafe2/fit/indexed/plot.py
kafe2/fit/io/__init__.py
kafe2/fit/io/file.py
kafe2/fit/io/handle.py
kafe2/fit/multi/__init__.py
kafe2/fit/multi/cost.py
kafe2/fit/multi/fit.py
kafe2/fit/representation/__init__.py
kafe2/fit/representation/_base.py
kafe2/fit/representation/_yaml_base.py
kafe2/fit/representation/constraint/__init__.py
kafe2/fit/representation/constraint/_base.py
kafe2/fit/representation/constraint/yaml_drepr.py
kafe2/fit/representation/container/__init__.py
kafe2/fit/representation/container/_base.py
kafe2/fit/representation/container/yaml_drepr.py
kafe2/fit/representation/error/__init__.py
kafe2/fit/representation/error/common_error_tools.py
kafe2/fit/representation/fit/__init__.py
kafe2/fit/representation/fit/_base.py
kafe2-2.11.0.dist-info/licenses/LICENSE
kafe2-2.11.0.dist-info/METADATA
kafe2-2.11.0.dist-info/WHEEL
kafe2-2.11.0.dist-info/entry_points.txt
kafe2-2.11.0.dist-info/top_level.txt
kafe2-2.11.0.dist-info/RECORD
