Metadata-Version: 2.4
Name: kafe2
Version: 2.11.0
Summary: Karlsruhe Fit Environment 2: a package for fitting and elementary data analysis
Author-email: Johannes Gäßler <johannes.gaessler@cern.ch>, Michael Hohenstein <michael@hohenste.in>, Günter Quast <G.Quast@kit.edu>, Daniel Savoiu <daniel.savoiu@cern.ch>, Cedric Verstege <cedric.verstege@cern.ch>
License-Expression: GPL-3.0-or-later
Project-URL: Homepage, https://philfitters.github.io/kafe2/
Project-URL: Repository, https://github.com/PhiLFitters/kafe2
Keywords: kafe2,kit,karlsruhe,data,analysis,lab,laboratory,practical courses,education,university,students,physics,fitting,minimization,minimisation,regression,parametric,parameter,estimation,optimization,optimisation
Classifier: Development Status :: 5 - Production/Stable
Classifier: Intended Audience :: Education
Classifier: Intended Audience :: Science/Research
Classifier: Topic :: Education
Classifier: Topic :: Scientific/Engineering
Classifier: Topic :: Scientific/Engineering :: Physics
Classifier: Topic :: Scientific/Engineering :: Information Analysis
Classifier: Topic :: Scientific/Engineering :: Visualization
Classifier: Programming Language :: Python :: 3
Classifier: Programming Language :: Python :: 3.6
Classifier: Programming Language :: Python :: 3.7
Classifier: Programming Language :: Python :: 3.8
Classifier: Programming Language :: Python :: 3.9
Classifier: Programming Language :: Python :: 3.10
Requires-Python: >=3.6
License-File: LICENSE
Requires-Dist: iminuit
Requires-Dist: NumPy
Requires-Dist: Numdifftools
Requires-Dist: Scipy
Requires-Dist: tabulate
Requires-Dist: matplotlib>=3.4
Requires-Dist: PyYaml
Requires-Dist: six
Requires-Dist: funcsigs
Requires-Dist: SymPy
Provides-Extra: dev
Requires-Dist: coverage; extra == "dev"
Requires-Dist: sphinx; extra == "dev"
Requires-Dist: sphinx-rtd-theme; extra == "dev"
Requires-Dist: mock; extra == "dev"
Requires-Dist: pytest; extra == "dev"
Requires-Dist: flake8; extra == "dev"
Requires-Dist: black; extra == "dev"
Requires-Dist: isort; extra == "dev"
Requires-Dist: build; extra == "dev"
Requires-Dist: twine; extra == "dev"
Requires-Dist: tomli; extra == "dev"
Requires-Dist: jupyterlab; extra == "dev"
Dynamic: license-file
